zinifile.py
zinifile-1.0.4.dist-info/METADATA
zinifile-1.0.4.dist-info/RECORD
zinifile-1.0.4.dist-info/WHEEL
zinifile-1.0.4.dist-info/top_level.txt
