Metadata-Version: 2.1
Name: zinifile
Version: 1.0.4
Summary: 操作更方便的配置文件读取模块
Home-page: https://pypi.org/
Author: zlyuan
Author-email: 1277260932@qq.com
License: GNU GENERAL PUBLIC LICENSE
Platform: all
Classifier: Environment :: Web Environment
Classifier: Intended Audience :: Developers
Classifier: Operating System :: OS Independent
Classifier: Programming Language :: Python
Classifier: Programming Language :: Python :: 3
Classifier: Programming Language :: Python :: 3.5
Classifier: Programming Language :: Python :: 3.6
